_examples/__init__.py
examples/__init__.py
plugitin/__init__.py
plugitin/aggregate_plugin.py
plugitin/chain_plugin.py
plugitin/plugin.py
plugitin/pyfs.py
plugitin/spec.py
plugitin/codegen/__init__.py
plugitin/codegen/cli.py
plugitin/codegen/logic.py
plugitin/finder/__init__.py
plugitin/finder/base.py
plugitin/finder/fs.py
plugitin/finder/name.py
plugitin/loader/__init__.py
plugitin/loader/base.py
plugitin/loader/fs.py
plugitin/loader/module.py
plugitin/metas/__init__.py
plugitin/metas/base.py
plugitin/metas/fs.py
plugitin/metas/module.py
tests/__init__.py
tests/config.py
tests/fsutils.py
tests/test_aggregate.py
tests/test_chain.py
tests/test_codegen.py
tests/test_fs_finder.py
tests/test_fs_loader.py
tests/test_name_finder.py
tests/test_py_module_loader.py
plugitin-0.1.0.dist-info/LICENSE.md
plugitin-0.1.0.dist-info/METADATA
plugitin-0.1.0.dist-info/WHEEL
plugitin-0.1.0.dist-info/entry_points.txt
plugitin-0.1.0.dist-info/top_level.txt
plugitin-0.1.0.dist-info/RECORD
